mkdocs_multiple/__init__.py
mkdocs_multiple/plugin.py
mkdocs_multiple-0.1.dist-info/LICENSE
mkdocs_multiple-0.1.dist-info/METADATA
mkdocs_multiple-0.1.dist-info/WHEEL
mkdocs_multiple-0.1.dist-info/entry_points.txt
mkdocs_multiple-0.1.dist-info/top_level.txt
mkdocs_multiple-0.1.dist-info/RECORD
