Metadata-Version: 2.1
Name: mkdocs-multiple
Version: 0.1
Summary: Allows to merge different mkdocs sources
Home-page: UNKNOWN
Author: Benjamin Piwowarski
Author-email: benjamin@piwowarski.fr
License: MIT
Keywords: mkdocs
Platform: UNKNOWN
Classifier: Development Status :: 5 - Production/Stable
Classifier: Intended Audience :: Developers
Classifier: Intended Audience :: Information Technology
Classifier: License :: OSI Approved :: MIT License
Classifier: Programming Language :: Python
Classifier: Programming Language :: Python :: 3 :: Only
Classifier: Programming Language :: Python :: 3.5
Classifier: Programming Language :: Python :: 3.6
Classifier: Programming Language :: Python :: 3.7
Requires-Python: >=3.5
Requires-Dist: mkdocs (>=1)
